[
  {
    "title": "Darknet Trusted Links",
    "content": "Darknet Trusted Links\n         \n        http://xttzwwygbav6pbqeyjm3k2vemhl5zomlwdgz43w3axhpn2pqyokjzyqd.onion/\n         \n        Free460",
    "info": "Posted by Anonymous at 09 Sep 2022, 09:49:54 UTC",
    "id": 0
  },
  {
    "title": "2.4TB",
    "content": "2.4TB PHOTO SETS AND VIDEOS\nhttp://dvst26jb6o6su3huisba5757pbhyrv6hbgo3y5rfzzohqfq73geujzad.onion",
    "info": "Posted by Anonymous at 09 Sep 2022, 09:46:19 UTC",
    "id": 1
  },
  {
    "title": "Exploit Live Scanner",
    "content": "http://k3phr3ag4vk63knm5xcopskebrhpfjyq6dx24x2do653vtmrd27mivid.onion/",
    "info": "Posted by Anonymous at 09 Sep 2022, 09:04:48 UTC",
    "id": 2
  },
  {
    "title": "Anonymous marketplace",
    "content": "Anonymous marketplace + guaranted secure escrow system\n \nhttp://sr4rya7za4kvocstuc7s2ed3f6tlsqbx4o5afdtqyjl4b3uzb5o23xad.onion/",
    "info": "Posted by Anonymous at 09 Sep 2022, 09:03:32 UTC",
    "id": 3
  },
  {
    "title": "Darknet Trusted Links",
    "content": "Darknet Trusted Links\n     \n    http://xttzwwygbav6pbqeyjm3k2vemhl5zomlwdgz43w3axhpn2pqyokjzyqd.onion/\n     \n    Free460",
    "info": "Posted by Anonymous at 09 Sep 2022, 09:00:07 UTC",
    "id": 4
  },
  {
    "title": "Darknet Trusted Links",
    "content": "Darknet Trusted Links\n \nhttp://xttzwwygbav6pbqeyjm3k2vemhl5zomlwdgz43w3axhpn2pqyokjzyqd.onion/\n \nFree460",
    "info": "Posted by Anonymous at 09 Sep 2022, 08:59:15 UTC",
    "id": 5
  },
  {
    "title": "CP CHEAP",
    "content": "http://exchangehd5455aori4qvrwhyno4ul7xrz4foy6qwga3olnbclp5f4qd.onion/?v9hkm2",
    "info": "Posted by Anonymous at 09 Sep 2022, 08:48:09 UTC",
    "id": 6
  },
  {
    "title": "Russian Community",
    "content": "http://commudazrdyhbullltfdy222krfjhoqzizks5ejmocpft3ijtxq5khqd.onion",
    "info": "Posted by Anonymous at 09 Sep 2022, 08:38:54 UTC",
    "id": 7
  },
  {
    "title": "Darknet Trusted Links",
    "content": "Darknet Trusted Links\n         \n        http://xttzwwygbav6pbqeyjm3k2vemhl5zomlwdgz43w3axhpn2pqyokjzyqd.onion/",
    "info": "Posted by Anonymous at 09 Sep 2022, 07:31:15 UTC",
    "id": 8
  },
  {
    "title": "Darknet Trusted Links",
    "content": "Darknet Trusted Links\n     \n    http://xttzwwygbav6pbqeyjm3k2vemhl5zomlwdgz43w3axhpn2pqyokjzyqd.onion/",
    "info": "Posted by Anonymous at 09 Sep 2022, 07:30:43 UTC",
    "id": 9
  },
  {
    "title": "DEEPMAGIC SHOP",
    "content": "DeepMagic Shop, sells best hashish pollen, buprenorphine (subutex), cocaine,more a section dedicated to all what is knowed about deepweb.I have been in the deep since 2011 (silk road 1) I decided to open my own site that I built myself, I am very honest I sell in different markets, but I am satisfied if users migrate to my site, I sell by email I have two emails one for clearweb and one for deepweb but I expect my users to use pgp when they contact me by email, just take a look at what I have done with my very little knowledge of html and css I have not used programs to make the site but only the knowledge that I remember even if I am very inexperienced I am satisfied wit",
    "info": "Posted by Anonymous at 09 Sep 2022, 06:25:53 UTC",
    "id": 10
  }
]
